PyXMake/Plugin/__build.py
PyXMake/Plugin/__git.py
PyXMake/Plugin/__gitlab.py
PyXMake/Plugin/__init__.py
PyXMake/Plugin/__poetry.py
pyx_poetry-1.28.1.dist-info/METADATA
pyx_poetry-1.28.1.dist-info/WHEEL
pyx_poetry-1.28.1.dist-info/entry_points.txt
pyx_poetry-1.28.1.dist-info/RECORD
